[
    {
        "title": "Тестим дальше) #4часть - YouTubehttps://www.youtube.com › watch",
        "domain": "www.youtube.com",
        "href": "https://www.youtube.com/watch%3Fv%3D8vSZMc0Suu4",
        "query": "тестим дальше",
        "position": 0,
        "meta": {
            "title": "https://www.youtube.com/watch%3Fv%3D8vSZMc0Suu4",
            "h1": ""
        }
    },
    {
        "title": "Brawl Stars ТЕСТИМ ДАЛЬШЕ НОВУЮ ИГРУ - YouTubehttps://m.youtube.com › watch",
        "domain": "m.youtube.com",
        "href": "https://m.youtube.com/watch%3Fv%3DZDJ7Z6LK_L4",
        "query": "тестим дальше",
        "position": 1,
        "meta": {
            "title": "https://m.youtube.com/watch%3Fv%3DZDJ7Z6LK_L4",
            "h1": ""
        }
    },
    {
        "title": "[RUS] F1 2017. Тестим дальше... - YouTubehttps://www.youtube.com › watch",
        "domain": "www.youtube.com",
        "href": "https://www.youtube.com/watch%3Fv%3DHFf9jEC-0Ng",
        "query": "тестим дальше",
        "position": 2,
        "meta": {
            "title": "https://www.youtube.com/watch%3Fv%3DHFf9jEC-0Ng",
            "h1": ""
        }
    },
    {
        "title": "GradusNeadekvata - Пока что тестим, а дальше как пойдет - Twitchhttps://www.twitch.tv › videos",
        "domain": "www.twitch.tv",
        "href": "https://www.twitch.tv/videos/278253680",
        "query": "тестим дальше",
        "position": 3,
        "meta": {
            "title": "Twitch",
            "h1": ""
        }
    },
    {
        "title": "SUPERSTAR тестим дальше часть 2 | Auto body repair - Pinteresthttps://www.pinterest.com › pin",
        "domain": "www.pinterest.com",
        "href": "https://www.pinterest.com/pin/293648838177108332/",
        "query": "тестим дальше",
        "position": 4,
        "meta": {
            "title": "SUPERSTAR тестим дальше часть 2 | Auto body repair | Auto body repair, Chevrolet logo, Chevrolet",
            "description": "This Pin was discovered by Евгений Жидков. Discover (and save!) your own Pins on Pinterest.",
            "h1": ""
        }
    },
    {
        "title": "тестим дальше: dr_transhttps://dr-trans.livejournal.com › ...",
        "domain": "dr-trans.livejournal.com",
        "href": "https://dr-trans.livejournal.com/564463.html",
        "query": "тестим дальше",
        "position": 5,
        "meta": {
            "title": "тестим дальше: dr_trans — LiveJournal",
            "description": "Проверочка DW → LH → FB",
            "h1": "      тестим дальше  LJ Magazine"
        }
    },
    {
        "title": "Iwata Supernova WS400 EVO 1.4 HD тестим дальше) - Видео ...https://vmire.life › video",
        "domain": "vmire.life",
        "href": "https://vmire.life/video/31IenogRDJk",
        "query": "тестим дальше",
        "position": 6,
        "meta": {
            "title": "Iwata Supernova WS400 EVO 1.4 HD тестим дальше) - Видео онлайн",
            "description": " ",
            "keywords": "филмлар, Скачать YouTube видео, скачать YouTube, скачать бесплатно, фильмы YouTube, узбек кино 2018, узбек кино 2018, русские фильмы 2018, русские фильмы 2017, турецкие фильмы, сериалы,",
            "h1": "Iwata Supernova WS400 EVO 1.4 HD тестим дальше)"
        }
    },
    {
        "title": "Тести на державну службу - Онлайн тестування - Відповідіhttps://testderz.com",
        "domain": "testderz.com",
        "href": "https://testderz.com/",
        "query": "тестим дальше",
        "position": 7,
        "meta": {
            "title": "",
            "description": "Пробні онлайн тести та відповіді на посади держслужби, Національну поліцію, Прокуратуру, НАБУ, Державне бюро розслідувань (ДБР). Тести на знання державної мови",
            "h1": "\n                            \n\t\t\t\t\t\t\t\tТести на державну службу                            \n                        "
        }
    },
    {
        "title": "Тест на беременность онлайн с точностью более 90%https://pregnancytestonline.org › ru-ua",
        "domain": "pregnancytestonline.org",
        "href": "https://pregnancytestonline.org/ru-ua/",
        "query": "тестим дальше",
        "position": 8,
        "meta": {
            "title": "Тест на беременность онлайн с точностью более 90%",
            "description": "Беременна ли я? Пройдите тест на беременность онлайн при любых подозрениях на беременность и узнайте ответ прямо сейчас, бесплатно, без СМС",
            "keywords": "тест на беременность",
            "h1": "Тест на беременность онлайн"
        }
    }
]